wits/__init__.py
wits-0.0.1.dist-info/METADATA
wits-0.0.1.dist-info/WHEEL
wits-0.0.1.dist-info/top_level.txt
wits-0.0.1.dist-info/RECORD
