Metadata-Version: 2.1
Name: wits
Version: 0.0.1
Summary: Brain Computations in Python
Home-page: https://github.com/wits-ai/wits/
Author: Wits AI
Author-email: eyalgl@gmail.com
License: UNKNOWN
Platform: UNKNOWN
Classifier: Programming Language :: Python :: 3.9
Requires-Dist: numpy
Requires-Dist: pandas
